setup.py
yacbv/__init__.py
yacbv/decorators.py
yacbv/mixins.py
yacbv/views.py
yacbv.egg-info/PKG-INFO
yacbv.egg-info/SOURCES.txt
yacbv.egg-info/dependency_links.txt
yacbv.egg-info/not-zip-safe
yacbv.egg-info/requires.txt
yacbv.egg-info/top_level.txt